dask_lsf/__init__.py
dask_lsf/dask_lsf.py
dask_lsf-1.1.1.dist-info/LICENSE
dask_lsf-1.1.1.dist-info/METADATA
dask_lsf-1.1.1.dist-info/WHEEL
dask_lsf-1.1.1.dist-info/top_level.txt
dask_lsf-1.1.1.dist-info/RECORD
