Metadata-Version: 2.1
Name: dask-lsf
Version: 1.1.1
Summary: APIs to enable lsf jobs from python using dask
Home-page: https://github.com/akarshanarora/dask_lsf
Author: Akarshan Arora
Author-email: akarshanarora@gmail.com
License: Apache Software License 2.0
Keywords: dask_lsf,dask,lsf,EDA,VLSI
Platform: UNKNOWN
Classifier: Development Status :: 5 - Production/Stable
Classifier: Intended Audience :: Developers
Classifier: License :: OSI Approved :: Apache Software License
Classifier: Natural Language :: English
Classifier: Programming Language :: Python :: 3
Classifier: Programming Language :: Python :: 3.6
Classifier: Programming Language :: Python :: 3.7
Classifier: Programming Language :: Python :: 3.8
Requires-Python: >=3.6
Requires-Dist: dask
Requires-Dist: dask-jobqueue
